saxtract/__init__.py
saxtract/cli.py
saxtract/saxtract.py
saxtract-0.1.0.dist-info/AUTHORS.rst
saxtract-0.1.0.dist-info/LICENSE
saxtract-0.1.0.dist-info/METADATA
saxtract-0.1.0.dist-info/WHEEL
saxtract-0.1.0.dist-info/entry_points.txt
saxtract-0.1.0.dist-info/top_level.txt
saxtract-0.1.0.dist-info/RECORD
