Metadata-Version: 2.1
Name: saxtract
Version: 0.1.0
Summary: Python SAX parser to extract xml
Home-page: https://github.com/danwald/saxtract
Author: danny crasto
Author-email: danwald79@gmail.com
License: MIT license
Keywords: saxtract
Platform: UNKNOWN
Classifier: Development Status :: 2 - Pre-Alpha
Classifier: Intended Audience :: Developers
Classifier: License :: OSI Approved :: MIT License
Classifier: Natural Language :: English
Classifier: Programming Language :: Python :: 3
Classifier: Programming Language :: Python :: 3.8
Requires-Python: >=3.8
License-File: LICENSE
License-File: AUTHORS.rst
Requires-Dist: Click (>=7.0)
